my_pkg/__init__.py
my_pkg/read_tydex.py
read_tydex_file_pkg-0.0.2.dist-info/LICENCE.md
read_tydex_file_pkg-0.0.2.dist-info/METADATA
read_tydex_file_pkg-0.0.2.dist-info/WHEEL
read_tydex_file_pkg-0.0.2.dist-info/top_level.txt
read_tydex_file_pkg-0.0.2.dist-info/RECORD
