Metadata-Version: 2.1
Name: read-tydex-file-pkg
Version: 0.0.2
Summary: A package for reading tydex file
Home-page: https://github.com/
Author: Xuyi Shi
Author-email: usyqu@kit.student.edu
Classifier: Programming Language :: Python :: 3
Classifier: License :: OSI Approved :: MIT License
Classifier: Operating System :: OS Independent
Requires-Python: >=3.6
License-File: LICENCE.md
